prometheus_coin_scraper/PrometheusClient.py
prometheus_coin_scraper/__init__.py
prometheus_coin_scrapper-0.0.2.dist-info/LICENSE.txt
prometheus_coin_scrapper-0.0.2.dist-info/METADATA
prometheus_coin_scrapper-0.0.2.dist-info/WHEEL
prometheus_coin_scrapper-0.0.2.dist-info/top_level.txt
prometheus_coin_scrapper-0.0.2.dist-info/RECORD
