Metadata-Version: 2.1
Name: prometheus-coin-scrapper
Version: 0.0.2
Summary: A simple prometheus scrapper that provide many information about cryptocurrencies values in "realtime"
Home-page: https://github.com/Willena/python-prometheus-coin-scrapper
Author: Guillaume VILLENA
Author-email: contact@guillaumevillena.fr
License: UNKNOWN
Project-URL: Funding, https://paypal.me/GuillaumeVillena
Project-URL: Bug Reports, https://github.com/Willena/python-prometheus-coin-scrapper/issues
Project-URL: Say Thanks!, https://paypal.me/GuillaumeVillena
Project-URL: Source, https://github.com/Willena/python-prometheus-coin-scrapper
Keywords: prometheus coin coin360 scrapper
Platform: UNKNOWN
Classifier: Development Status :: 4 - Beta
Classifier: Intended Audience :: Developers
Classifier: Topic :: System :: Monitoring
Classifier: License :: OSI Approved :: MIT License
Classifier: Programming Language :: Python :: 2
Classifier: Programming Language :: Python :: 2.7
Classifier: Programming Language :: Python :: 3
Classifier: Programming Language :: Python :: 3.4
Classifier: Programming Language :: Python :: 3.5
Classifier: Programming Language :: Python :: 3.6
Classifier: Programming Language :: Python :: 3.7
Requires-Dist: prometheus-client
Requires-Dist: requests
Requires-Dist: cryptocurrencies-scraper
